tableschema_sql/VERSION
tableschema_sql/__init__.py
tableschema_sql/mapper.py
tableschema_sql/storage.py
tableschema_sql/writer.py
tableschema_sql-2.0.1.dist-info/LICENSE.md
tableschema_sql-2.0.1.dist-info/METADATA
tableschema_sql-2.0.1.dist-info/WHEEL
tableschema_sql-2.0.1.dist-info/top_level.txt
tableschema_sql-2.0.1.dist-info/RECORD
