Metadata-Version: 2.1
Name: tableschema-sql
Version: 2.0.1
Summary: Generate SQL tables, load and extract data, based on JSON Table Schema descriptors.
Home-page: https://github.com/frictionlessdata/tableschema-sql-py
Author: Open Knowledge Foundation
Author-email: info@okfn.org
License: MIT
Keywords: frictionless data
Platform: UNKNOWN
Classifier: Development Status :: 4 - Beta
Classifier: Environment :: Web Environment
Classifier: Intended Audience :: Developers
Classifier: License :: OSI Approved :: MIT License
Classifier: Operating System :: OS Independent
Classifier: Programming Language :: Python :: 2
Classifier: Programming Language :: Python :: 2.7
Classifier: Programming Language :: Python :: 3
Classifier: Programming Language :: Python :: 3.3
Classifier: Programming Language :: Python :: 3.4
Classifier: Programming Language :: Python :: 3.5
Classifier: Topic :: Internet :: WWW/HTTP :: Dynamic Content
Classifier: Topic :: Software Development :: Libraries :: Python Modules
Provides-Extra: develop
License-File: LICENSE.md
